Workbook

Sheet Build Plan
A1: AI Interior Makeover: capabilities and build estimate
A2: Stack: Bolt (front end), Supabase (backend), AI image-editing API. Edit blue cells (tokens, hours); totals update.
A4: # | B4: Capability | C4: Priority | D4: Approach | E4: Tools | F4: Build tokens (approx.) | G4: Time (hours) | H4: Tokens low | I4: Tokens high | J4: Labour cost (₹)
A5: 1 | B5: Sign-up and login | C5: MVP | D5: Email and Google sign-in; row-level security so each user sees only their own rooms and designs | E5: Bolt, Supabase Auth | F5: 25000 | G5: 1 | H5: =F5*(1-Assumptions!$B$3) -> 15000 | I5: =F5*(1+Assumptions!$B$3) -> 35000 | J5: =G5*Cost!$B$5 -> 600
A6: 2 | B6: Room photo upload | C6: MVP | D6: Drag-and-drop upload, JPG/PNG up to 10 MB, client-side resize before upload, stored per user | E6: Bolt, Supabase Storage | F6: 30000 | G6: 1.5 | H6: =F6*(1-Assumptions!$B$3) -> 18000 | I6: =F6*(1+Assumptions!$B$3) -> 42000 | J6: =G6*Cost!$B$5 -> 900
A7: 3 | B7: Style selection | C7: MVP | D7: Style picker (Modern, Scandinavian, Japandi, Boho, Industrial, Traditional Indian) backed by a table of prompt templates | E7: Bolt, Supabase Postgres | F7: 20000 | G7: 1 | H7: =F7*(1-Assumptions!$B$3) -> 12000 | I7: =F7*(1+Assumptions!$B$3) -> 28000 | J7: =G7*Cost!$B$5 -> 600
A8: 4 | B8: AI makeover generation | C8: MVP | D8: Edge Function sends the photo plus the style prompt to the image-editing API and returns 2-3 variants; the API key stays server-side | E8: Supabase Edge Functions, OpenAI image edit API (or similar) | F8: 80000 | G8: 4 | H8: =F8*(1-Assumptions!$B$3) -> 48000 | I8: =F8*(1+Assumptions!$B$3) -> 112000 | J8: =G8*Cost!$B$5 -> 2400
A9: 5 | B9: Progress, errors and usage limits | C9: MVP | D9: Loading state with style previews, retry on failure, daily generation quota per user to control cost | E9: Bolt, Supabase tables and Edge Function | F9: 30000 | G9: 2 | H9: =F9*(1-Assumptions!$B$3) -> 18000 | I9: =F9*(1+Assumptions!$B$3) -> 42000 | J9: =G9*Cost!$B$5 -> 1200
A10: 6 | B10: Before/after slider | C10: MVP | D10: Draggable overlay comparing the original with the chosen concept | E10: Bolt (React component) | F10: 25000 | G10: 1.5 | H10: =F10*(1-Assumptions!$B$3) -> 15000 | I10: =F10*(1+Assumptions!$B$3) -> 35000 | J10: =G10*Cost!$B$5 -> 900
A11: 7 | B11: Personal gallery | C11: MVP | D11: Save, rename, favourite and delete designs; thumbnails loaded from storage | E11: Bolt, Supabase Postgres and Storage | F11: 40000 | G11: 2 | H11: =F11*(1-Assumptions!$B$3) -> 24000 | I11: =F11*(1+Assumptions!$B$3) -> 56000 | J11: =G11*Cost!$B$5 -> 1200
A12: 8 | B12: Share link and family vote | C12: Differentiator | D12: Public read-only page per design with a vote button; votes stored per concept | E12: Bolt, Supabase Postgres | F12: 45000 | G12: 2.5 | H12: =F12*(1-Assumptions!$B$3) -> 27000 | I12: =F12*(1+Assumptions!$B$3) -> 63000 | J12: =G12*Cost!$B$5 -> 1500
A13: 9 | B13: Budget Mode | C13: Differentiator | D13: User enters a budget in ₹; the text model returns structured JSON of changes with estimated costs that fit the budget | E13: OpenAI API (structured output), Edge Function | F13: 50000 | G13: 3 | H13: =F13*(1-Assumptions!$B$3) -> 30000 | I13: =F13*(1+Assumptions!$B$3) -> 70000 | J13: =G13*Cost!$B$5 -> 1800
A14: 10 | B14: Shop the Look | C14: Differentiator | D14: Each suggested item gets a search link to a retailer, built from the item name; no scraping | E14: OpenAI API, Bolt | F14: 35000 | G14: 2 | H14: =F14*(1-Assumptions!$B$3) -> 21000 | I14: =F14*(1+Assumptions!$B$3) -> 49000 | J14: =G14*Cost!$B$5 -> 1200
A15: 11 | B15: Vastu overlay | C15: Differentiator | D15: Vision model reads the photo and returns layout suggestions as short notes; shown beside the concept | E15: OpenAI vision API, Edge Function | F15: 40000 | G15: 2 | H15: =F15*(1-Assumptions!$B$3) -> 24000 | I15: =F15*(1+Assumptions!$B$3) -> 56000 | J15: =G15*Cost!$B$5 -> 1200
A16: 12 | B16: Landing page and demo gallery | C16: Polish | D16: Hero section, pre-generated sample makeovers for the demo, responsive layout | E16: Bolt | F16: 40000 | G16: 2.5 | H16: =F16*(1-Assumptions!$B$3) -> 24000 | I16: =F16*(1+Assumptions!$B$3) -> 56000 | J16: =G16*Cost!$B$5 -> 1500
A17: 13 | B17: Testing, deploy and demo rehearsal | C17: Polish | D17: Fix bugs, test on phone, deploy, rehearse the live reveal with a fallback gallery | E17: Bolt hosting or Netlify, Supabase dashboard | F17: 50000 | G17: 3 | H17: =F17*(1-Assumptions!$B$3) -> 30000 | I17: =F17*(1+Assumptions!$B$3) -> 70000 | J17: =G17*Cost!$B$5 -> 1800
B19: Summary by priority
B20: Priority | C20: Capabilities | F20: Build tokens | G20: Time (hours) | H20: Tokens low | I20: Tokens high | J20: Labour cost (₹)
B21: MVP | C21: =COUNTIF($C$5:$C$17,B21) -> 7 | F21: =SUMIF($C$5:$C$17,B21,F$5:F$17) -> 250000 | G21: =SUMIF($C$5:$C$17,B21,G$5:G$17) -> 13 | H21: =SUMIF($C$5:$C$17,B21,H$5:H$17) -> 150000 | I21: =SUMIF($C$5:$C$17,B21,I$5:I$17) -> 350000 | J21: =SUMIF($C$5:$C$17,B21,J$5:J$17) -> 7800
B22: Differentiator | C22: =COUNTIF($C$5:$C$17,B22) -> 4 | F22: =SUMIF($C$5:$C$17,B22,F$5:F$17) -> 170000 | G22: =SUMIF($C$5:$C$17,B22,G$5:G$17) -> 9.5 | H22: =SUMIF($C$5:$C$17,B22,H$5:H$17) -> 102000 | I22: =SUMIF($C$5:$C$17,B22,I$5:I$17) -> 238000 | J22: =SUMIF($C$5:$C$17,B22,J$5:J$17) -> 5700
B23: Polish | C23: =COUNTIF($C$5:$C$17,B23) -> 2 | F23: =SUMIF($C$5:$C$17,B23,F$5:F$17) -> 90000 | G23: =SUMIF($C$5:$C$17,B23,G$5:G$17) -> 5.5 | H23: =SUMIF($C$5:$C$17,B23,H$5:H$17) -> 54000 | I23: =SUMIF($C$5:$C$17,B23,I$5:I$17) -> 126000 | J23: =SUMIF($C$5:$C$17,B23,J$5:J$17) -> 3300
B24: Total | C24: =SUM(C21:C23) -> 13 | F24: =SUM(F21:F23) -> 510000 | G24: =SUM(G21:G23) -> 28 | H24: =SUM(H21:H23) -> 306000 | I24: =SUM(I21:I23) -> 714000 | J24: =SUM(J21:J23) -> 16800
B26: Total working days (1 developer) | G26: =G24/Assumptions!$B$5 -> 3.5
B27: Time with parallel developers (hours) | G27: =G21+G23+G22/Assumptions!$B$4 -> 23.25
B29: Cash cost: tools and AI API (₹) | G29: =Cost!E37 -> 6147.02
B30: Total cost of implementation incl. labour (₹) | G30: =Cost!E39 -> 22947.02

Sheet Assumptions
A1: Assumptions (edit the blue cells)
A3: Token estimate margin (±) | B3: 0.4 | C3: Build-token counts are rough; low/high columns apply this margin.
A4: Developers working in parallel | B4: 2 | C4: Used for the parallel time estimate.
A5: Hours per working day | B5: 8 | C5: Used to convert hours to days.
A8: Notes
A9: Tokens are build tokens only: prompts to Bolt, generated code and debugging rounds. Source: Claude's estimate, not measured.
A10: Time is working hours for one person. Source: Claude's estimate.
A11: Parallel estimate assumes only Differentiators (8-11) can be split across developers; MVP and Polish stay sequential.
A12: Running cost per generation is separate: one image-edit call plus about 2,000-3,000 text tokens when Budget Mode and Vastu are on. Check the image API's current price before the demo.
A13: Cut order if time runs short: drop 11, then 10, then 8; keep 9 only if the budget pitch is central.

Sheet Cost
A1: Cost of implementing AI Interior Makeover
A2: Edit the blue cells; every cost below recalculates. Rates are assumptions or published prices as of Oct 2026 and can change.
A3: Inputs
A4: USD to INR rate | B4: 88 | C4: Assumption. Check the current rate.
A5: Developer hourly rate (₹) | B5: 600 | C5: Placeholder. Set to your own rate, or 0 if your own time is free.
A6: Bolt Pro plan (USD per month) | B6: 25 | C6: Bolt Pro: $25/month for 10M tokens, no daily cap. Free plan: 1M tokens/month with a 300K daily cap. Source: jetadmin.io Bolt pricing guide (Jul 2026).
A7: Bolt Pro months needed | B7: 1 | C7: The full build (about 510K tokens, up to 714K) fits within one month of Pro.
A8: Supabase Pro (USD per month) | B8: 25 | C8: Supabase Pro: $25/month. Free plan: 1 GB file storage, 500 MB database. Source: jetadmin.io Supabase pricing guide (Jul 2026).
A9: Supabase Pro months needed | B9: 1 | C9: Set to 0 to stay on the Free plan; room photos and designs fill 1 GB quickly.
A10: Image output tokens per image (medium, 1024x1024) | B10: 439 | C10: GPT Image 2.5 Sunburst: low 196, medium 439, high 1,756 tokens. Source: docs.kanaries.net (cites OpenAI's estimator).
A11: Image output price (USD per 1M tokens) | B11: 30 | C11: OpenAI standard rate; $15 with Batch. Source: developers.openai.com/api/docs/models/gpt-image-2.5-sunburst.
A12: Room photo input tokens per call | B12: 1000 | C12: Assumption. OpenAI has not published this for 2.5; read the usage field from real calls.
A13: Image input price (USD per 1M tokens) | B13: 8 | C13: OpenAI rate for GPT Image 2.5 Sunburst.
A14: Prompt tokens per call | B14: 60 | C14: Kanaries estimate for a short prompt.
A15: Text input price (USD per 1M tokens) | B15: 5 | C15: OpenAI rate for GPT Image 2.5 Sunburst.
... A20: Text-model price (USD per 1M tokens) | B20: 5 | C20: Assumption: uses the $5 text rate above. Your chosen model may differ.
A22: Derived rates
A23: Cost per image (USD) | B23: =B10*B11/1000000+B12*B13/1000000+B14*B15/1000000 -> 0.02147
A24: Text cost per generation (USD) | B24: =B19*B20/1000000 -> 0.015
A25: Cost per generation (₹) | B25: =(B16*B23+B24)*B4 -> 6.98808
A26: Cost per 1,000 generations (₹) | B26: =B25*1000 -> 6988.08
A28: Cost breakdown
A29: Category | B29: Item | C29: Quantity | D29: Unit cost (₹) | E29: Cost (₹) | F29: Basis
A30: Tools | B30: Bolt Pro subscription (months) | C30: =B7 -> 1 | D30: =B6*B4 -> 2200 | E30: =C30*D30 -> 2200 | F30: Plan price x months
A31: Tools | B31: Supabase Pro (months) | C31: =B9 -> 1 | D31: =B8*B4 -> 2200 | E31: =C31*D31 -> 2200 | F31: Plan price x months
A32: Tools | B32: Hosting (Bolt hosting or Netlify free tier) | C32: 1 | D32: 0 | E32: =C32*D32 -> 0 | F32: Free tier assumed
A33: AI API | B33: Test generations during the build | C33: =B17 -> 150 | D33: =B25 -> 6.98808 | E33: =C33*D33 -> 1048.212 | F33: Cost per generation x count
A34: AI API | B34: Demo and judging generations | C34: =B18 -> 100 | D34: =B25 -> 6.98808 | E34: =C34*D34 -> 698.808 | F34: Cost per generation x count
A35: Labour | B35: Development hours (from Build Plan) | C35: ='Build Plan'!G24 -> 28 | D35: =B5 -> 600 | E35: =C35*D35 -> 16800 | F35: Total hours x hourly rate
A37: Cash cost: tools and AI API | E37: =SUM(E30:E34) -> 6147.02
A38: Labour cost | E38: =E35 -> 16800
A39: Total cost of implementation | E39: =E37+E38 -> 22947.02
A40: Cash cost if Bolt and Supabase stay on free tiers | E40: =E33+E34 -> 1747.02
A42: Notes
A43: gpt-image-1 was retired on Oct 23, 2026; the estimate uses its replacement, GPT Image 2.5 Sunburst, which supports image edits.
A44: OpenAI publishes no edit-specific per-image price for 2.5, so image cost is output tokens plus an assumed reference-photo input. Log usage on real calls to confirm.
A45: Costs exclude GST, payment fees and any custom domain. Bolt build tokens (about 510K) are covered by the plan price and not billed separately.
A46: Running cost after launch is the cost per generation (B25), multiplied by your expected usage.
